[
  {
    "centre": "IGS",
    "product_id": "igs_orbit",
    "spec": "ORBIT",
    "server": "ftp://igs.ign.fr",
    "protocol": "ftp",
    "directory": "pub/igs/products/2349/",
    "filename": "IGS0OPSFIN_20250150000_01D_15M_ORB.SP3.gz"
  },
  {
    "centre": "IGS",
    "product_id": "igs_orbit",
    "spec": "ORBIT",
    "server": "ftp://igs.ign.fr",
    "protocol": "ftp",
    "directory": "pub/igs/products/2349/",
    "filename": "IGS0OPSRAP_20250150000_01D_15M_ORB.SP3.gz"
  },
  {
    "centre": "IGS",
    "product_id": "igs_clock",
    "spec": "CLOCK",
    "server": "ftp://igs.ign.fr",
    "protocol": "ftp",
    "directory": "pub/igs/products/2349/",
    "filename": "IGS0OPSFIN_20250150000_01D_30S_CLK.CLK.gz"
  },
  {
    "centre": "IGS",
    "product_id": "igs_clock",
    "spec": "CLOCK",
    "server": "ftp://igs.ign.fr",
    "protocol": "ftp",
    "directory": "pub/igs/products/2349/",
    "filename": "IGS0OPSFIN_20250150000_01D_05M_CLK.CLK.gz"
  },
  {
    "centre": "IGS",
    "product_id": "igs_clock",
    "spec": "CLOCK",
    "server": "ftp://igs.ign.fr",
    "protocol": "ftp",
    "directory": "pub/igs/products/2349/",
    "filename": "IGS0OPSRAP_20250150000_01D_05M_CLK.CLK.gz"
  },
  {
    "centre": "IGS",
    "product_id": "igs_erp",
    "spec": "ERP",
    "server": "ftp://igs.ign.fr",
    "protocol": "ftp",
    "directory": "pub/igs/products/2349/",
    "filename": "IGS0OPSRAP_20250150000_01D_01D_ERP.ERP.gz"
  },
  {
    "centre": "IGS",
    "product_id": "igs_nav",
    "spec": "RNX3_BRDC",
    "server": "ftp://igs.ign.fr",
    "protocol": "ftp",
    "directory": "pub/igs/data/2025/015/",
    "filename": "BRDC00IGS_R_20250150000_01D_MN.rnx.gz"
  },
  {
    "centre": "WUM",
    "product_id": "wuhan_orbit",
    "spec": "ORBIT",
    "server": "ftp://igs.gnsswhu.cn",
    "protocol": "ftp",
    "directory": "pub/whu/phasebias/2025/orbit/",
    "filename": "WUM0MGXRAP_20250150000_01D_05M_ORB.SP3.gz"
  },
  {
    "centre": "WUM",
    "product_id": "wuhan_orbit",
    "spec": "ORBIT",
    "server": "ftp://igs.gnsswhu.cn",
    "protocol": "ftp",
    "directory": "pub/whu/phasebias/2025/orbit/",
    "filename": "WMC0DEMFIN_20250150000_01D_05M_ORB.SP3.gz"
  },
  {
    "centre": "WUM",
    "product_id": "wuhan_orbit",
    "spec": "ORBIT",
    "server": "ftp://igs.gnsswhu.cn",
    "protocol": "ftp",
    "directory": "pub/whu/phasebias/2025/orbit/",
    "filename": "WMC0DEMRAP_20250150000_01D_05M_ORB.SP3.gz"
  },
  {
    "centre": "WUM",
    "product_id": "wuhan_clock",
    "spec": "CLOCK",
    "server": "ftp://igs.gnsswhu.cn",
    "protocol": "ftp",
    "directory": "pub/whu/phasebias/2025/clock/",
    "filename": "WUM0MGXRAP_20250150000_01D_30S_CLK.CLK.gz"
  },
  {
    "centre": "WUM",
    "product_id": "wuhan_clock",
    "spec": "CLOCK",
    "server": "ftp://igs.gnsswhu.cn",
    "protocol": "ftp",
    "directory": "pub/whu/phasebias/2025/clock/",
    "filename": "WMC0DEMFIN_20250150000_01D_30S_CLK.CLK.gz"
  },
  {
    "centre": "WUM",
    "product_id": "wuhan_clock",
    "spec": "CLOCK",
    "server": "ftp://igs.gnsswhu.cn",
    "protocol": "ftp",
    "directory": "pub/whu/phasebias/2025/clock/",
    "filename": "WMC0DEMRAP_20250150000_01D_30S_CLK.CLK.gz"
  },
  {
    "centre": "WUM",
    "product_id": "wuhan_erp",
    "spec": "ERP",
    "server": "ftp://igs.gnsswhu.cn",
    "protocol": "ftp",
    "directory": "pub/whu/phasebias/2025/orbit/",
    "filename": "WUM0MGXRAP_20250150000_01D_01D_ERP.ERP.gz"
  },
  {
    "centre": "WUM",
    "product_id": "wuhan_bias",
    "spec": "BIA",
    "server": "ftp://igs.gnsswhu.cn",
    "protocol": "ftp",
    "directory": "pub/whu/phasebias/2025/bias/",
    "filename": "WUM0MGXRAP_20250150000_01D_01D_OSB.BIA.gz"
  },
  {
    "centre": "WUM",
    "product_id": "wuhan_bias",
    "spec": "BIA",
    "server": "ftp://igs.gnsswhu.cn",
    "protocol": "ftp",
    "directory": "pub/whu/phasebias/2025/bias/",
    "filename": "WMC0DEMFIN_20250150000_01D_01D_OSB.BIA.gz"
  },
  {
    "centre": "WUM",
    "product_id": "wuhan_bias",
    "spec": "BIA",
    "server": "ftp://igs.gnsswhu.cn",
    "protocol": "ftp",
    "directory": "pub/whu/phasebias/2025/bias/",
    "filename": "WMC0DEMRAP_20250150000_01D_01D_OSB.BIA.gz"
  },
  {
    "centre": "WUM",
    "product_id": "wuhan_obx",
    "spec": "ATTOBX",
    "server": "ftp://igs.gnsswhu.cn",
    "protocol": "ftp",
    "directory": "pub/whu/phasebias/2025/orbit/",
    "filename": "WMC0DEMFIN_20250150000_01D_30S_ATT.OBX.gz"
  },
  {
    "centre": "WUM",
    "product_id": "wuhan_gim",
    "spec": "IONEX",
    "server": "ftp://igs.gnsswhu.cn",
    "protocol": "ftp",
    "directory": "pub/gps/products/ionex/2025/015/",
    "filename": "COD0OPSFIN_20250150000_01D_01H_GIM.INX.gz"
  },
  {
    "centre": "WUM",
    "product_id": "wuhan_gim",
    "spec": "IONEX",
    "server": "ftp://igs.gnsswhu.cn",
    "protocol": "ftp",
    "directory": "pub/gps/products/ionex/2025/015/",
    "filename": "COD0OPSRAP_20250150000_01D_01H_GIM.INX.gz"
  },
  {
    "centre": "WUM",
    "product_id": "wuhan_gim",
    "spec": "IONEX",
    "server": "ftp://igs.gnsswhu.cn",
    "protocol": "ftp",
    "directory": "pub/gps/products/ionex/2025/015/",
    "filename": "IGS0OPSFIN_20250150000_01D_02H_GIM.INX.gz"
  },
  {
    "centre": "WUM",
    "product_id": "wuhan_gim",
    "spec": "IONEX",
    "server": "ftp://igs.gnsswhu.cn",
    "protocol": "ftp",
    "directory": "pub/gps/products/ionex/2025/015/",
    "filename": "IGS0OPSRAP_20250150000_01D_02H_GIM.INX.gz"
  },
  {
    "centre": "WUM",
    "product_id": "wuhan_gim",
    "spec": "IONEX",
    "server": "ftp://igs.gnsswhu.cn",
    "protocol": "ftp",
    "directory": "pub/gps/products/ionex/2025/015/",
    "filename": "JPL0OPSFIN_20250150000_01D_02H_GIM.INX.gz"
  },
  {
    "centre": "WUM",
    "product_id": "wuhan_gim",
    "spec": "IONEX",
    "server": "ftp://igs.gnsswhu.cn",
    "protocol": "ftp",
    "directory": "pub/gps/products/ionex/2025/015/",
    "filename": "JPL0OPSRAP_20250150000_01D_02H_GIM.INX.gz"
  },
  {
    "centre": "WUM",
    "product_id": "wuhan_leap_seconds",
    "spec": "LEAP_SEC",
    "server": "ftp://igs.gnsswhu.cn",
    "protocol": "ftp",
    "directory": "pub/whu/phasebias/table",
    "filename": "leap.sec"
  },
  {
    "centre": "WUM",
    "product_id": "wuhan_sat_parameters",
    "spec": "SAT_PARAMS",
    "server": "ftp://igs.gnsswhu.cn",
    "protocol": "ftp",
    "directory": "pub/whu/phasebias/table",
    "filename": "sat_parameters"
  }
]